pyxdf_mne/__init__.py
pyxdf_mne/main.py
pyxdf_mne-0.0.2.dist-info/LICENSE
pyxdf_mne-0.0.2.dist-info/METADATA
pyxdf_mne-0.0.2.dist-info/WHEEL
pyxdf_mne-0.0.2.dist-info/top_level.txt
pyxdf_mne-0.0.2.dist-info/RECORD
